clify/__init__.py
clify/app.py
clify/command.py
clify/daemon.py
clify/test/__init__.py
clify/test/base.py
clify/test/test_application.py
clify-0.0.1.dist-info/DESCRIPTION.rst
clify-0.0.1.dist-info/METADATA
clify-0.0.1.dist-info/RECORD
clify-0.0.1.dist-info/WHEEL
clify-0.0.1.dist-info/metadata.json
clify-0.0.1.dist-info/pbr.json
clify-0.0.1.dist-info/top_level.txt
