Metadata-Version: 2.0
Name: clify
Version: 0.0.1
Summary: Python Command Line Framework built on argparse
Home-page: https://github.com/rmb938/clify
Author: Ryan Belgrave
Author-email: rmb1993@gmail.com
License: MIT
Platform: UNKNOWN
Classifier: Development Status :: 3 - Alpha
Classifier: Environment :: Console
Classifier: Intended Audience :: Developers
Classifier: License :: OSI Approved :: MIT License
Classifier: Operating System :: OS Independent
Classifier: Programming Language :: Python
Classifier: Topic :: Software Development :: Libraries :: Application Frameworks
